MANIFEST.in
README.rst
setup.py
etc/qnupload/qnupload.conf
src/qnupload/__init__.py
src/qnupload/qnupload.py
src/qnupload.egg-info/PKG-INFO
src/qnupload.egg-info/SOURCES.txt
src/qnupload.egg-info/dependency_links.txt
src/qnupload.egg-info/entry_points.txt
src/qnupload.egg-info/requires.txt
src/qnupload.egg-info/top_level.txt